<?xml version="1.0" encoding="UTF-8"?><record_update table="x_1310794_founda_0_issue_rules">
    <x_1310794_founda_0_issue_rules action="INSERT_OR_UPDATE">
        <active>true</active>
        <code>DUPLICATE</code>
        <default_severity>medium</default_severity>
        <description>Détecte les enregistrements dupliqués basés sur des champs clés. Utilisez params {"key_fields": "name,code"} pour spécifier les champs qui définissent l'unicité.</description>
        <name>Duplicate Record</name>
        <params>{"key_fields":"name"}</params>
        <script><![CDATA[var keyFields = params.key_fields || 'name';
var fields = keyFields.split(',').map(function(f){ return (f || '').trim(); });

var keyParts = [];
fields.forEach(function(f) {
    keyParts.push(item.values[f] || '');
});
var key = keyParts.join('|');

var seen = context && context._dupsSeen;
if (!seen) return issues;

if (seen[key] && seen[key] !== item.sys_id) {
    var recordName = item.values.name || item.values.title || 'Record';
    var message = 'Doublon détecté: "' + recordName + '" a les mêmes ' + fields.join(', ') + ' qu\'un autre enregistrement. Cela peut causer des conflits.';
    
    issues.push({
        code: rule.code,
        message: message,
        severity: rule.severity || 'medium',
        details: { 
            duplicate_of: seen[key],
            key_fields: fields,
            key_value: key,
            record_table: item.table,
            record_sys_id: item.sys_id,
            record_name: recordName,
            recommendation: 'Renommer ou fusionner avec l\'enregistrement dupliqué'
        }
    });
}]]></script>
        <severity>medium</severity>
        <sys_class_name>x_1310794_founda_0_issue_rules</sys_class_name>
        <sys_created_by>admin</sys_created_by>
        <sys_created_on>2026-01-18 12:00:00</sys_created_on>
        <sys_id>aaaa0005feed53163610c7233ee0a049</sys_id>
        <sys_mod_count>0</sys_mod_count>
        <sys_name>Duplicate Record</sys_name>
        <sys_package display_value="Foundation Health Analyzer" source="x_1310794_founda_0">d852994c8312321083e1b4a6feaad3e6</sys_package>
        <sys_policy>read</sys_policy>
        <sys_scope display_value="Foundation Health Analyzer">d852994c8312321083e1b4a6feaad3e6</sys_scope>
        <sys_update_name>x_1310794_founda_0_issue_rules_aaaa0005feed53163610c7233ee0a049</sys_update_name>
        <sys_updated_by>admin</sys_updated_by>
        <sys_updated_on>2026-01-18 12:00:00</sys_updated_on>
        <type>duplicate</type>
    </x_1310794_founda_0_issue_rules>
</record_update>
